equities/__init__.py
equities/data/__init__.py
enigma_12312-2.1.10.dist-info/LICENSE
enigma_12312-2.1.10.dist-info/METADATA
enigma_12312-2.1.10.dist-info/WHEEL
enigma_12312-2.1.10.dist-info/top_level.txt
enigma_12312-2.1.10.dist-info/RECORD
