Metadata-Version: 2.1
Name: enigma-12312
Version: 2.1.10
Summary: placeholder.
Home-page: https://github.com/ljc-codes/equities.git
Author: Tiger_Shark
Author-email: na@gmail.com
License: UNKNOWN
Platform: UNKNOWN
Classifier: Programming Language :: Python :: 3
Classifier: License :: OSI Approved :: MIT License
Classifier: Operating System :: OS Independent
Requires-Python: >=3.6
Requires-Dist: alive-progress (==1.6.1)
Requires-Dist: chardet (==3.0.4)
Requires-Dist: idna (==2.7)
Requires-Dist: isort (==4.3.4)
Requires-Dist: matplotlib (==3.2.0)
Requires-Dist: numpy (==1.18.0)
Requires-Dist: pandas (==1.0.1)
Requires-Dist: psutil (==5.6.2)
Requires-Dist: pytz (==2018.5)
Requires-Dist: requests (==2.21.0)
Requires-Dist: six (==1.11.0)
Requires-Dist: tqdm (==4.43.0)
Requires-Dist: wrapt (==1.10.11)
